{
   "replayCreators": [
      {
         "id": "cr_001",
         "name": "Inside Football",
         "event_type":"sport",
         "teaser":"",
         "thumbnail": "https://firebasestorage.googleapis.com/v0/b/jeli-a53be.appspot.com/o/evisel%2Fsoccer3.jpg?alt=media&token=b8e5ce5b-0f3a-4648-8356-19d315e940d5",
         "metrics": {
            "followers": 48200,
            "subscribers": 18300
         },
         "verified": true,
         "channel": {
            "canonical_url": "/replay/creators/inside-football",
            "profile_image": "https://firebasestorage.googleapis.com/v0/b/jeli-a53be.appspot.com/o/evisel%2Fsoccer1.jpg?alt=media&token=85af6aad-8743-4ef9-9597-0cf33dd7cb85",
            "name": "Inside Football",
            "description": "Analyses tactiques, inside clubs et interviews exclusives."
         },
         "replays": [
            {
               "id": "rep_001_1",
               "title": "Débrief J10 – Ligue 1",
               "date": "2025-10-12T20:30:00+02:00",
               "thumbnail": "https://evisel-tv.fr/wp-content/uploads/2025/10/550825108_1156884656557254_2600194261612656895_n.jpg",
               "teaser":"",
               "stereo":true,
               "description": "Emission complète en VOD",
               "url": "https://cdn.jumpr.fr/KSW/out/playlist.m3u8"
            },
            {
               "id": "rep_001_2",
               "title": "Interview – Jeune crack à suivre",
               "date": "2025-10-15T18:00:00+02:00",
               "thumbnail": "https://firebasestorage.googleapis.com/v0/b/jeli-a53be.appspot.com/o/evisel%2Fsoccer3.jpg?alt=media&token=b8e5ce5b-0f3a-4648-8356-19d315e940d5",
               "teaser":"",
               "stereo":false,
               "description": "Format court 12 min",
               "url": "https://cdn.jumpr.fr/KSW-113//out/4k_avc/stream.m3u8
"
            },
            {
               "id": "rep_001_3",
               "title": "Top buts du mois",
               "date": "2025-09-30T21:00:00+02:00",
               "thumbnail": "https://firebasestorage.googleapis.com/v0/b/jeli-a53be.appspot.com/o/evisel%2Fsoccer1.jpg?alt=media&token=85af6aad-8743-4ef9-9597-0cf33dd7cb85",
               "teaser":"",
               "stereo":false,
               "description": "Les plus beaux gestes",
               "url": "https://cdn.jumpr.fr/InsideFoot_TopButs/playlist.m3u8"
            }
         ]
      },
      {
         "id": "cr_002",
         "name": "Bakary Gym",
         "event_type":"sport",
         "teaser":"",
         "thumbnail": "https://evisel-tv.fr/wp-content/uploads/2025/10/558995744_1104559571658571_7556524691112463794_n.jpg",
         "metrics": {
            "followers": 25700,
            "subscribers": 12100
         },
         "verified": false,
         "channel": {
            "canonical_url": "/replay/creators/bakary-gym",
            "profile_image": "https://evisel-tv.fr/wp-content/uploads/2025/10/558995744_1104559571658571_7556524691112463794_n.jpg",
            "name": "Bakary Gym",
            "description": "Prépa physique, nutrition et coulisses d’un boxeur pro."
         },
         "replays": [
            {
               "id": "rep_002_1",
               "title": "Sparring à haute intensité",
               "date": "2025-10-10T17:00:00+02:00",
               "thumbnail": "https://evisel-tv.fr/wp-content/uploads/2025/10/558995744_1104559571658571_7556524691112463794_n.jpg",
               "teaser":"",                  
               "stereo":false,
               "description": "Caméra au bord du ring",
               "url": "https://cdn.jumpr.fr/Bakary_Ring/playlist.m3u8"
            },
            {
               "id": "rep_002_2",
               "title": "Routine d’entraînement – Épaules",
               "date": "2025-10-05T11:00:00+02:00",
               "thumbnail": "https://firebasestorage.googleapis.com/v0/b/jeli-a53be.appspot.com/o/evisel%2Fsoccer3.jpg?alt=media&token=b8e5ce5b-0f3a-4648-8356-19d315e940d5",
               "teaser":"",
               "stereo":false,
               "description": "Séance guidée 25 min",
               "url": "https://cdn.jumpr.fr/Bakary_Workout/playlist.m3u8"
            }
         ]
      },
      {
         "id": "cr_003",
         "name": "Jeudi Electro",
         "event_type":"music",
         "teaser":"",
         "thumbnail": "https://www.festivaloffavignon.com/data/spectacles/5564-zmJgPjmxaak29E8CYihX-catalogue.png",
         "metrics": {
            "followers": 33400,
            "subscribers": 15600
         },
         "verified": true,
         "channel": {
            "canonical_url": "/replay/creators/jeudi-electro",
            "profile_image": "https://www.festivaloffavignon.com/data/spectacles/5564-zmJgPjmxaak29E8CYihX-catalogue.png",
            "name": "Jeudi Electro",
            "description": "Sets live, warm-ups et aftermovies en replay."
         },
         "replays": [
            {
               "id": "rep_003_1",
               "title": "Warm-up – Opening Night",
               "date": "2025-10-01T20:00:00+02:00",
               "thumbnail": "https://www.festivaloffavignon.com/data/spectacles/5564-zmJgPjmxaak29E8CYihX-catalogue.png",
               "teaser":"",
               "stereo":false,
               "description": "Set 45 min",
               "url": "https://cdn.jumpr.fr/Jeudi_Warmup/playlist.m3u8"
            },
            {
               "id": "rep_003_2",
               "title": "Aftermovie – Été 2025",
               "date": "2025-09-15T18:00:00+02:00",
               "thumbnail": "https://firebasestorage.googleapis.com/v0/b/jeli-a53be.appspot.com/o/evisel%2Fsoccer1.jpg?alt=media&token=85af6aad-8743-4ef9-9597-0cf33dd7cb85",
               "teaser":"",
               "stereo":false,
               "description": "Les meilleurs moments",
               "url": "https://cdn.jumpr.fr/Jeudi_Aftermovie/playlist.m3u8"
            }
         ]
      },
      {
         "id": "cr_004",
         "name": "Paris Culture Live",
         "event_type":"culture",
         "thumbnail": "https://firebasestorage.googleapis.com/v0/b/jeli-a53be.appspot.com/o/evisel%2Fsoccer1.jpg?alt=media&token=85af6aad-8743-4ef9-9597-0cf33dd7cb85",
         "metrics": {
            "followers": 12800,
            "subscribers": 5200
         },
         "verified": false,
         "channel": {
            "canonical_url": "/replay/creators/paris-culture-live",
            "profile_image": "https://firebasestorage.googleapis.com/v0/b/jeli-a53be.appspot.com/o/evisel%2Fsoccer1.jpg?alt=media&token=85af6aad-8743-4ef9-9597-0cf33dd7cb85",
            "name": "Paris Culture Live",
            "description": "Visites guidées d'expos et coulisses culturelles."
         },
         "replays": [
            {
               "id": "rep_004_1",
               "title": "Expo immersive – Parcours guidé",
               "date": "2025-09-28T16:00:00+02:00",
               "thumbnail": "https://firebasestorage.googleapis.com/v0/b/jeli-a53be.appspot.com/o/evisel%2Fsoccer3.jpg?alt=media&token=b8e5ce5b-0f3a-4648-8356-19d315e940d5",
               "teaser":"",
               "stereo":false,
               "description": "Visite live au cœur des œuvres.",
               "url": "https://cdn.jumpr.fr/ExpoV2/playlist.m3u8"
            }
         ]
      }
   ]
}
